[{"id":"member-1.mdx","slug":"member-1","body":"","collection":"teams","data":{"name":"my name is","designation":"my designation","description":"this is a descripton for dynamic data","imageUrl":"demo1.png","social":["social1","social2"],"tags":["one","two"]}},{"id":"member-2.mdx","slug":"member-2","body":"","collection":"teams","data":{"name":"fiverr freelancing project","designation":"full stack developer","description":"different descripton for dynamic data","imageUrl":"demo2.png","social":["social1","social2"],"tags":["three","two","one"]}}]